{
 "accountAgentId": "1",
 "accountEntityId": "1",
 "accountId": "BUCO",
 "amount": {
  "basecurrency": "zar",
  "basevalu": "526423259.29",
  "currency": "zar",
  "value": "526423259.29"
 },
 "counterpartyEntityId": "8577",
 "counterpartyId": "12055",
 "customerEntityId": "customerEntityId_1",
 "customerId": "BUCO",
 "direction": "Outbound",
 "eventId": "6eb3fd70-5639-4388-8cdf-0a9c4a04f442",
 "eventTime": "2023-05-23T20:18:45",
 "eventType": "paymentRT",
 "fromId": "African Bank Limited",
 "msgStatus": "New",
 "msgType": "2100",
 "numberOfTransactions": 1,
 "paymentFrequency": "11",
 "paymentMethod": "paymentMethod_1",
 "schemaVersion": 1,
 "settlementDate": "2023-05-23",
 "tenantId": "African Bank Limited",
 "toId": "2221008453109476",
 "transactionId": "6034a49b-bf7b-4bc6-9bc5-a8475c0fafa9",
 "transactionType": "proxy_push"
}